{
  "kind": "collectionType",
  "collectionName": "room-amenities",
  "info": {
    "singularName": "room-amenity",
    "pluralName": "room-amenities",
    "displayName": "Удобства в Номерах"
  },
  "attributes": {
    "name": {
      "type": "string",
      "required": true,
      "unique": true
    },
    "sort": {
      "type": "integer"
    },
    "slug": {
      "type": "string",
      "required": true,
      "unique": true
    },
    "image": {
      "allowedTypes": [
        "images"
      ],
      "type": "media",
      "multiple": false
    }
  }
}